spwn/__init__.py
spwn/analyzer.py
spwn/binary.py
spwn/configgenerator.py
spwn/configmanager.py
spwn/customanalyzer.py
spwn/filemanager.py
spwn/libc.py
spwn/loader.py
spwn/scripter.py
spwn/spwn.py
spwn/utils.py
spwn-1.2.5.dist-info/LICENSE
spwn-1.2.5.dist-info/METADATA
spwn-1.2.5.dist-info/WHEEL
spwn-1.2.5.dist-info/entry_points.txt
spwn-1.2.5.dist-info/top_level.txt
spwn-1.2.5.dist-info/RECORD
