Metadata-Version: 2.1
Name: spwn
Version: 1.2.5
Summary: Automatic tool to quickly start a pwn CTF challenge
Home-page: https://github.com/MarcoMeinardi/spwn
Author: Chino
Classifier: Environment :: Console
Classifier: Operating System :: POSIX :: Linux
Classifier: Programming Language :: Python :: 3
Classifier: Topic :: Security
Classifier: Topic :: Software Development :: Code Generators
License-File: LICENSE
Requires-Dist: pwntools
Requires-Dist: yara-python
